spacex/starlink/__init__.py
spacex/starlink/alert.py
spacex/starlink/dish.py
spacex/starlink/outage_reason.py
spacex/starlink/status.py
starlink_python-0.1.2.dist-info/METADATA
starlink_python-0.1.2.dist-info/WHEEL
starlink_python-0.1.2.dist-info/top_level.txt
starlink_python-0.1.2.dist-info/RECORD
