Metadata-Version: 2.1
Name: starlink-python
Version: 0.1.2
Summary: Connect to SpaceX Starlink
Home-page: https://github.com/pacorain/starlink-python
Author: Austin Rainwater
Author-email: hey@paco.wtf
License: UNKNOWN
Project-URL: Bug Tracker, https://github.com/pacorain/starlink-python/issues
Platform: UNKNOWN
Classifier: Programming Language :: Python :: 3
Classifier: License :: OSI Approved :: MIT License
Classifier: Development Status :: 3 - Alpha
Classifier: License :: Public Domain
Classifier: Topic :: Home Automation
Classifier: Operating System :: OS Independent
Requires-Dist: grpcio
Requires-Dist: yagrc
